<annotation>
	<folder>detect</folder>
	<filename>image_171.jpg</filename>
	<path>C:\Start\ВНО\_Распознавание кораблей с использованием нейросетей\NewDATA_1\images\detect\image_171.jpg</path>
	<source>
		<database>Unknown</database>
	</source>
	<size>
		<width>640</width>
		<height>480</height>
		<depth>3</depth>
	</size>
	<segmented>0</segmented>
	<object>
		<name>person</name>
		<pose>Unspecified</pose>
		<truncated>0</truncated>
		<difficult>0</difficult>
		<bndbox>
			<xmin>490</xmin>
			<ymin>261</ymin>
			<xmax>510</xmax>
			<ymax>289</ymax>
		</bndbox>
	</object>
	<object>
		<name>person</name>
		<pose>Unspecified</pose>
		<truncated>0</truncated>
		<difficult>0</difficult>
		<bndbox>
			<xmin>337</xmin>
			<ymin>50</ymin>
			<xmax>350</xmax>
			<ymax>82</ymax>
		</bndbox>
	</object>
	<object>
		<name>person</name>
		<pose>Unspecified</pose>
		<truncated>0</truncated>
		<difficult>0</difficult>
		<bndbox>
			<xmin>164</xmin>
			<ymin>134</ymin>
			<xmax>183</xmax>
			<ymax>162</ymax>
		</bndbox>
	</object>
	<object>
		<name>person</name>
		<pose>Unspecified</pose>
		<truncated>0</truncated>
		<difficult>0</difficult>
		<bndbox>
			<xmin>64</xmin>
			<ymin>163</ymin>
			<xmax>91</xmax>
			<ymax>200</ymax>
		</bndbox>
	</object>
</annotation>
